{"v":"5.7.4","fr":60,"ip":0,"op":480,"w":1440,"h":900,"nm":"Loading-Motion-2","ddd":0,"assets":[],"layers":[{"ddd":0,"ind":1,"ty":1,"nm":"Square","sr":1,"ks":{"o":{"a":0,"k":100,"ix":11},"r":{"a":1,"k":[{"i":{"x":[0.833],"y":[0.833]},"o":{"x":[0.167],"y":[0.167]},"t":-4,"s":[0]},{"i":{"x":[0.833],"y":[0.833]},"o":{"x":[0.167],"y":[0.167]},"t":11,"s":[90]},{"i":{"x":[0.833],"y":[0.833]},"o":{"x":[0.167],"y":[0.167]},"t":26,"s":[180]},{"i":{"x":[0.833],"y":[0.833]},"o":{"x":[0.167],"y":[0.167]},"t":41,"s":[270]},{"i":{"x":[0.833],"y":[0.833]},"o":{"x":[0.167],"y":[0.167]},"t":56,"s":[360]},{"i":{"x":[0.833],"y":[0.833]},"o":{"x":[0.167],"y":[0.167]},"t":71,"s":[450]},{"i":{"x":[0.833],"y":[0.833]},"o":{"x":[0.167],"y":[0.167]},"t":86,"s":[540]},{"i":{"x":[0.833],"y":[0.833]},"o":{"x":[0.167],"y":[0.167]},"t":101,"s":[630]},{"i":{"x":[0.833],"y":[0.833]},"o":{"x":[0.167],"y":[0.167]},"t":116,"s":[720]},{"i":{"x":[0.833],"y":[0.833]},"o":{"x":[0.167],"y":[0.167]},"t":131,"s":[810]},{"i":{"x":[0.833],"y":[0.833]},"o":{"x":[0.167],"y":[0.167]},"t":146,"s":[900]},{"i":{"x":[0.833],"y":[0.833]},"o":{"x":[0.167],"y":[0.167]},"t":161,"s":[990]},{"i":{"x":[0.833],"y":[0.833]},"o":{"x":[0.167],"y":[0.167]},"t":176,"s":[1080]},{"i":{"x":[0.833],"y":[0.833]},"o":{"x":[0.167],"y":[0.167]},"t":191,"s":[1170]},{"i":{"x":[0.833],"y":[0.833]},"o":{"x":[0.167],"y":[0.167]},"t":206,"s":[1260]},{"i":{"x":[0.833],"y":[0.833]},"o":{"x":[0.167],"y":[0.167]},"t":221,"s":[1350]},{"i":{"x":[0.833],"y":[0.833]},"o":{"x":[0.167],"y":[0.167]},"t":236,"s":[1440]},{"i":{"x":[0.833],"y":[0.833]},"o":{"x":[0.167],"y":[0.167]},"t":251,"s":[1530]},{"i":{"x":[0.833],"y":[0.833]},"o":{"x":[0.167],"y":[0.167]},"t":266,"s":[1620]},{"i":{"x":[0.833],"y":[0.833]},"o":{"x":[0.167],"y":[0.167]},"t":281,"s":[1710]},{"i":{"x":[0.833],"y":[0.833]},"o":{"x":[0.167],"y":[0.167]},"t":295,"s":[1800]},{"i":{"x":[0.833],"y":[0.833]},"o":{"x":[0.167],"y":[0.167]},"t":311,"s":[1890]},{"i":{"x":[0.833],"y":[0.833]},"o":{"x":[0.167],"y":[0.167]},"t":326,"s":[1980]},{"i":{"x":[0.833],"y":[0.833]},"o":{"x":[0.167],"y":[0.167]},"t":341,"s":[2070]},{"i":{"x":[0.833],"y":[0.833]},"o":{"x":[0.167],"y":[0.167]},"t":356,"s":[2160]},{"i":{"x":[0.833],"y":[0.833]},"o":{"x":[0.167],"y":[0.167]},"t":371,"s":[2250]},{"i":{"x":[0.833],"y":[0.833]},"o":{"x":[0.167],"y":[0.167]},"t":386,"s":[2340]},{"i":{"x":[0.833],"y":[0.833]},"o":{"x":[0.167],"y":[0.167]},"t":401,"s":[2430]},{"i":{"x":[0.833],"y":[0.833]},"o":{"x":[0.167],"y":[0.167]},"t":416,"s":[2520]},{"i":{"x":[0.833],"y":[0.833]},"o":{"x":[0.167],"y":[0.167]},"t":431,"s":[2610]},{"i":{"x":[0.833],"y":[0.833]},"o":{"x":[0.167],"y":[0.167]},"t":446,"s":[2700]},{"i":{"x":[0.833],"y":[0.833]},"o":{"x":[0.167],"y":[0.167]},"t":461,"s":[2790]},{"t":476,"s":[2880]}],"ix":10},"p":{"a":1,"k":[{"i":{"x":0.833,"y":0.833},"o":{"x":0.167,"y":0.167},"t":-4,"s":[-4,559,0],"to":[0,0,0],"ti":[0,0,0]},{"i":{"x":0.833,"y":0.833},"o":{"x":0.167,"y":0.167},"t":11,"s":[-4,559,0],"to":[8.167,0,0],"ti":[-8.167,0,0]},{"i":{"x":0.833,"y":0.833},"o":{"x":0.167,"y":0.167},"t":13,"s":[45,559,0],"to":[0,0,0],"ti":[0,0,0]},{"i":{"x":0.833,"y":0.833},"o":{"x":0.167,"y":0.167},"t":26,"s":[45,559,0],"to":[8.167,0,0],"ti":[-8.167,0,0]},{"i":{"x":0.833,"y":0.833},"o":{"x":0.167,"y":0.167},"t":28,"s":[94,559,0],"to":[0,0,0],"ti":[0,0,0]},{"i":{"x":0.833,"y":0.833},"o":{"x":0.167,"y":0.167},"t":41,"s":[94,559,0],"to":[8.167,0,0],"ti":[-8.167,0,0]},{"i":{"x":0.833,"y":0.833},"o":{"x":0.167,"y":0.167},"t":43,"s":[143,559,0],"to":[0,0,0],"ti":[0,0,0]},{"i":{"x":0.833,"y":0.833},"o":{"x":0.167,"y":0.167},"t":56,"s":[143,559,0],"to":[8,0,0],"ti":[-8,0,0]},{"i":{"x":0.833,"y":0.833},"o":{"x":0.167,"y":0.167},"t":58,"s":[191,559,0],"to":[0,0,0],"ti":[0,0,0]},{"i":{"x":0.833,"y":0.833},"o":{"x":0.167,"y":0.167},"t":71,"s":[191,559,0],"to":[8.167,0,0],"ti":[-8.167,0,0]},{"i":{"x":0.833,"y":0.833},"o":{"x":0.167,"y":0.167},"t":73,"s":[240,559,0],"to":[0,0,0],"ti":[0,0,0]},{"i":{"x":0.833,"y":0.833},"o":{"x":0.167,"y":0.167},"t":86,"s":[240,559,0],"to":[8,0,0],"ti":[-8,0,0]},{"i":{"x":0.833,"y":0.833},"o":{"x":0.167,"y":0.167},"t":88,"s":[288,559,0],"to":[0,0,0],"ti":[0,0,0]},{"i":{"x":0.833,"y":0.833},"o":{"x":0.167,"y":0.167},"t":101,"s":[288,559,0],"to":[8,0,0],"ti":[-8,0,0]},{"i":{"x":0.833,"y":0.833},"o":{"x":0.167,"y":0.167},"t":103,"s":[336,559,0],"to":[0,0,0],"ti":[0,0,0]},{"i":{"x":0.833,"y":0.833},"o":{"x":0.167,"y":0.167},"t":116,"s":[336,559,0],"to":[8,0,0],"ti":[-8,0,0]},{"i":{"x":0.833,"y":0.833},"o":{"x":0.167,"y":0.167},"t":118,"s":[384,559,0],"to":[0,0,0],"ti":[0,0,0]},{"i":{"x":0.833,"y":0.833},"o":{"x":0.167,"y":0.167},"t":131,"s":[384,559,0],"to":[8,0,0],"ti":[-8,0,0]},{"i":{"x":0.833,"y":0.833},"o":{"x":0.167,"y":0.167},"t":133,"s":[432,559,0],"to":[0,0,0],"ti":[0,0,0]},{"i":{"x":0.833,"y":0.833},"o":{"x":0.167,"y":0.167},"t":146,"s":[432,559,0],"to":[8,0,0],"ti":[-8,0,0]},{"i":{"x":0.833,"y":0.833},"o":{"x":0.167,"y":0.167},"t":148,"s":[480,559,0],"to":[0,0,0],"ti":[0,0,0]},{"i":{"x":0.833,"y":0.833},"o":{"x":0.167,"y":0.167},"t":161,"s":[480,559,0],"to":[8.167,0,0],"ti":[-8.167,0,0]},{"i":{"x":0.833,"y":0.833},"o":{"x":0.167,"y":0.167},"t":163,"s":[529,559,0],"to":[0,0,0],"ti":[0,0,0]},{"i":{"x":0.833,"y":0.833},"o":{"x":0.167,"y":0.167},"t":176,"s":[529,559,0],"to":[7.724,0,0],"ti":[-7.724,0,0]},{"i":{"x":0.833,"y":0.833},"o":{"x":0.167,"y":0.167},"t":178,"s":[575.341,559,0],"to":[0,0,0],"ti":[0,0,0]},{"i":{"x":0.833,"y":0.833},"o":{"x":0.167,"y":0.167},"t":191,"s":[575.341,559,0],"to":[8.13,0,0],"ti":[-8.13,0,0]},{"i":{"x":0.833,"y":0.833},"o":{"x":0.167,"y":0.167},"t":193,"s":[624.122,559,0],"to":[0,0,0],"ti":[0,0,0]},{"i":{"x":0.833,"y":0.833},"o":{"x":0.167,"y":0.167},"t":206,"s":[624.122,559,0],"to":[8.537,0,0],"ti":[-8.537,0,0]},{"i":{"x":0.833,"y":0.833},"o":{"x":0.167,"y":0.167},"t":208,"s":[675.341,559,0],"to":[0,0,0],"ti":[0,0,0]},{"i":{"x":0.833,"y":0.833},"o":{"x":0.167,"y":0.167},"t":221,"s":[675.341,559,0],"to":[7.667,0,0],"ti":[-7.667,0,0]},{"i":{"x":0.833,"y":0.833},"o":{"x":0.167,"y":0.167},"t":223,"s":[721.341,559,0],"to":[0,0,0],"ti":[0,0,0]},{"i":{"x":0.833,"y":0.833},"o":{"x":0.167,"y":0.167},"t":236,"s":[721.341,559,0],"to":[8.667,0,0],"ti":[-8.667,0,0]},{"i":{"x":0.833,"y":0.833},"o":{"x":0.167,"y":0.167},"t":239,"s":[773.341,559,0],"to":[0,0,0],"ti":[0,0,0]},{"i":{"x":0.833,"y":0.833},"o":{"x":0.167,"y":0.167},"t":251,"s":[773.341,559,0],"to":[7.333,0,0],"ti":[-7.333,0,0]},{"i":{"x":0.833,"y":0.833},"o":{"x":0.167,"y":0.167},"t":254,"s":[817.341,559,0],"to":[0,0,0],"ti":[0,0,0]},{"i":{"x":0.833,"y":0.833},"o":{"x":0.167,"y":0.167},"t":266,"s":[817.341,559,0],"to":[7.667,0,0],"ti":[-7.667,0,0]},{"i":{"x":0.833,"y":0.833},"o":{"x":0.167,"y":0.167},"t":269,"s":[863.341,559,0],"to":[0,0,0],"ti":[0,0,0]},{"i":{"x":0.833,"y":0.833},"o":{"x":0.167,"y":0.167},"t":281,"s":[863.341,559,0],"to":[7.333,0,0],"ti":[-7.333,0,0]},{"i":{"x":0.833,"y":0.833},"o":{"x":0.167,"y":0.167},"t":284,"s":[907.341,559,0],"to":[0,0,0],"ti":[0,0,0]},{"i":{"x":0.833,"y":0.833},"o":{"x":0.167,"y":0.167},"t":295,"s":[907.341,559,0],"to":[7.667,0,0],"ti":[-7.667,0,0]},{"i":{"x":0.833,"y":0.833},"o":{"x":0.167,"y":0.167},"t":298,"s":[953.341,559,0],"to":[0,0,0],"ti":[0,0,0]},{"i":{"x":0.833,"y":0.833},"o":{"x":0.167,"y":0.167},"t":311,"s":[953.341,559,0],"to":[7.667,0,0],"ti":[-7.667,0,0]},{"i":{"x":0.833,"y":0.833},"o":{"x":0.167,"y":0.167},"t":314,"s":[999.341,559,0],"to":[0,0,0],"ti":[0,0,0]},{"i":{"x":0.833,"y":0.833},"o":{"x":0.167,"y":0.167},"t":326,"s":[999.341,559,0],"to":[7.333,0,0],"ti":[-7.333,0,0]},{"i":{"x":0.833,"y":0.833},"o":{"x":0.167,"y":0.167},"t":329,"s":[1043.341,559,0],"to":[0,0,0],"ti":[0,0,0]},{"i":{"x":0.833,"y":0.833},"o":{"x":0.167,"y":0.167},"t":341,"s":[1043.341,559,0],"to":[7.667,0,0],"ti":[-7.667,0,0]},{"i":{"x":0.833,"y":0.833},"o":{"x":0.167,"y":0.167},"t":344,"s":[1089.341,559,0],"to":[0,0,0],"ti":[0,0,0]},{"i":{"x":0.833,"y":0.833},"o":{"x":0.167,"y":0.167},"t":356,"s":[1089.341,559,0],"to":[7,0,0],"ti":[-7,0,0]},{"i":{"x":0.833,"y":0.833},"o":{"x":0.167,"y":0.167},"t":359,"s":[1131.341,559,0],"to":[0,0,0],"ti":[0,0,0]},{"i":{"x":0.833,"y":0.833},"o":{"x":0.167,"y":0.167},"t":371,"s":[1131.341,559,0],"to":[7.667,0,0],"ti":[-7.667,0,0]},{"i":{"x":0.833,"y":0.833},"o":{"x":0.167,"y":0.167},"t":374,"s":[1177.341,559,0],"to":[0,0,0],"ti":[0,0,0]},{"i":{"x":0.833,"y":0.833},"o":{"x":0.167,"y":0.167},"t":386,"s":[1177.341,559,0],"to":[7,0,0],"ti":[-7,0,0]},{"i":{"x":0.833,"y":0.833},"o":{"x":0.167,"y":0.167},"t":389,"s":[1219.341,559,0],"to":[0,0,0],"ti":[0,0,0]},{"i":{"x":0.833,"y":0.833},"o":{"x":0.167,"y":0.167},"t":401,"s":[1219.341,559,0],"to":[8,0,0],"ti":[-8,0,0]},{"i":{"x":0.833,"y":0.833},"o":{"x":0.167,"y":0.167},"t":404,"s":[1267.341,559,0],"to":[0,0,0],"ti":[0,0,0]},{"i":{"x":0.833,"y":0.833},"o":{"x":0.167,"y":0.167},"t":416,"s":[1267.341,559,0],"to":[7,0,0],"ti":[-7,0,0]},{"i":{"x":0.833,"y":0.833},"o":{"x":0.167,"y":0.167},"t":419,"s":[1309.341,559,0],"to":[0,0,0],"ti":[0,0,0]},{"i":{"x":0.833,"y":0.833},"o":{"x":0.167,"y":0.167},"t":431,"s":[1309.341,559,0],"to":[8,0,0],"ti":[-8,0,0]},{"i":{"x":0.833,"y":0.833},"o":{"x":0.167,"y":0.167},"t":434,"s":[1357.341,559,0],"to":[0,0,0],"ti":[0,0,0]},{"i":{"x":0.833,"y":0.833},"o":{"x":0.167,"y":0.167},"t":446,"s":[1357.341,559,0],"to":[7.333,0,0],"ti":[-7.333,0,0]},{"i":{"x":0.833,"y":0.833},"o":{"x":0.167,"y":0.167},"t":449,"s":[1401.341,559,0],"to":[0,0,0],"ti":[0,0,0]},{"i":{"x":0.833,"y":0.833},"o":{"x":0.167,"y":0.167},"t":461,"s":[1401.341,559,0],"to":[8,0,0],"ti":[-8,0,0]},{"i":{"x":0.833,"y":0.833},"o":{"x":0.167,"y":0.167},"t":464,"s":[1449.341,559,0],"to":[0,0,0],"ti":[0,0,0]},{"t":476,"s":[1449.341,559,0]}],"ix":2,"l":2},"a":{"a":1,"k":[{"i":{"x":0.833,"y":0.833},"o":{"x":0.167,"y":0.167},"t":-4,"s":[50,50,0],"to":[0,0,0],"ti":[0,0,0]},{"i":{"x":0.833,"y":1},"o":{"x":0.167,"y":0},"t":11,"s":[50,50,0],"to":[0,-8.167,0],"ti":[0,8.167,0]},{"i":{"x":0.833,"y":0.833},"o":{"x":0.167,"y":0.167},"t":13,"s":[50,1,0],"to":[0,0,0],"ti":[0,0,0]},{"i":{"x":0.833,"y":1},"o":{"x":0.167,"y":0},"t":26,"s":[50,1,0],"to":[-8.167,0,0],"ti":[8.167,0,0]},{"i":{"x":0.833,"y":0.833},"o":{"x":0.167,"y":0.167},"t":28,"s":[1,1,0],"to":[0,0,0],"ti":[0,0,0]},{"i":{"x":0.833,"y":1},"o":{"x":0.167,"y":0},"t":41,"s":[1,1,0],"to":[0,8.167,0],"ti":[0,-8.167,0]},{"i":{"x":0.833,"y":0.833},"o":{"x":0.167,"y":0.167},"t":43,"s":[1,50,0],"to":[0,0,0],"ti":[0,0,0]},{"i":{"x":0.833,"y":0.833},"o":{"x":0.167,"y":0.167},"t":56,"s":[1,50,0],"to":[8,0,0],"ti":[-8,0,0]},{"i":{"x":0.833,"y":0.833},"o":{"x":0.167,"y":0.167},"t":58,"s":[49,50,0],"to":[0,0,0],"ti":[0,0,0]},{"i":{"x":0.833,"y":1},"o":{"x":0.167,"y":0},"t":71,"s":[49,50,0],"to":[0,-8.167,0],"ti":[0,8.167,0]},{"i":{"x":0.833,"y":0.833},"o":{"x":0.167,"y":0.167},"t":73,"s":[49,1,0],"to":[0,0,0],"ti":[0,0,0]},{"i":{"x":0.833,"y":1},"o":{"x":0.167,"y":0},"t":86,"s":[49,1,0],"to":[-8,0,0],"ti":[8,0,0]},{"i":{"x":0.833,"y":0.833},"o":{"x":0.167,"y":0.167},"t":88,"s":[1,1,0],"to":[0,0,0],"ti":[0,0,0]},{"i":{"x":0.833,"y":1},"o":{"x":0.167,"y":0},"t":101,"s":[1,1,0],"to":[0,8,0],"ti":[0,-8,0]},{"i":{"x":0.833,"y":0.833},"o":{"x":0.167,"y":0.167},"t":103,"s":[1,49,0],"to":[0,0,0],"ti":[0,0,0]},{"i":{"x":0.833,"y":0.833},"o":{"x":0.167,"y":0.167},"t":116,"s":[1,49,0],"to":[8,0,0],"ti":[-8,0,0]},{"i":{"x":0.833,"y":0.833},"o":{"x":0.167,"y":0.167},"t":118,"s":[49,49,0],"to":[0,0,0],"ti":[0,0,0]},{"i":{"x":0.833,"y":1},"o":{"x":0.167,"y":0},"t":131,"s":[49,49,0],"to":[0,-8,0],"ti":[0,8,0]},{"i":{"x":0.833,"y":0.833},"o":{"x":0.167,"y":0.167},"t":133,"s":[49,1,0],"to":[0,0,0],"ti":[0,0,0]},{"i":{"x":0.833,"y":1},"o":{"x":0.167,"y":0},"t":146,"s":[49,1,0],"to":[-8,0,0],"ti":[8,0,0]},{"i":{"x":0.833,"y":0.833},"o":{"x":0.167,"y":0.167},"t":148,"s":[1,1,0],"to":[0,0,0],"ti":[0,0,0]},{"i":{"x":0.833,"y":1},"o":{"x":0.167,"y":0},"t":161,"s":[1,1,0],"to":[0,8.167,0],"ti":[0,-8.167,0]},{"i":{"x":0.833,"y":0.833},"o":{"x":0.167,"y":0.167},"t":163,"s":[1,50,0],"to":[0,0,0],"ti":[0,0,0]},{"i":{"x":0.833,"y":0.833},"o":{"x":0.167,"y":0.167},"t":176,"s":[1,50,0],"to":[7.724,0,0],"ti":[-7.724,0,0]},{"i":{"x":0.833,"y":0.833},"o":{"x":0.167,"y":0.167},"t":178,"s":[47.341,50,0],"to":[0,0,0],"ti":[0,0,0]},{"i":{"x":0.833,"y":1},"o":{"x":0.167,"y":0},"t":191,"s":[47.341,50,0],"to":[0,-8.13,0],"ti":[0,8.13,0]},{"i":{"x":0.833,"y":0.833},"o":{"x":0.167,"y":0.167},"t":193,"s":[47.341,1.22,0],"to":[0,0,0],"ti":[0,0,0]},{"i":{"x":0.833,"y":1},"o":{"x":0.167,"y":0},"t":206,"s":[47.341,1.22,0],"to":[-8.537,0,0],"ti":[8.537,0,0]},{"i":{"x":0.833,"y":0.833},"o":{"x":0.167,"y":0.167},"t":208,"s":[-3.878,1.22,0],"to":[0,0,0],"ti":[0,0,0]},{"i":{"x":0.833,"y":1},"o":{"x":0.167,"y":0},"t":221,"s":[-3.878,1.22,0],"to":[0,7.667,0],"ti":[0,-7.667,0]},{"i":{"x":0.833,"y":0.833},"o":{"x":0.167,"y":0.167},"t":223,"s":[-3.878,47.22,0],"to":[0,0,0],"ti":[0,0,0]},{"i":{"x":0.833,"y":0.833},"o":{"x":0.167,"y":0.167},"t":236,"s":[-3.878,47.22,0],"to":[8.667,0,0],"ti":[-8.667,0,0]},{"i":{"x":0.833,"y":0.833},"o":{"x":0.167,"y":0.167},"t":239,"s":[48.122,47.22,0],"to":[0,0,0],"ti":[0,0,0]},{"i":{"x":0.833,"y":1},"o":{"x":0.167,"y":0},"t":251,"s":[48.122,47.22,0],"to":[0,-7.333,0],"ti":[0,7.333,0]},{"i":{"x":0.833,"y":0.833},"o":{"x":0.167,"y":0.167},"t":254,"s":[48.122,3.22,0],"to":[0,0,0],"ti":[0,0,0]},{"i":{"x":0.833,"y":1},"o":{"x":0.167,"y":0},"t":266,"s":[48.122,3.22,0],"to":[-7.667,0,0],"ti":[7.667,0,0]},{"i":{"x":0.833,"y":0.833},"o":{"x":0.167,"y":0.167},"t":269,"s":[2.122,3.22,0],"to":[0,0,0],"ti":[0,0,0]},{"i":{"x":0.833,"y":1},"o":{"x":0.167,"y":0},"t":281,"s":[2.122,3.22,0],"to":[0,7.333,0],"ti":[0,-7.333,0]},{"i":{"x":0.833,"y":0.833},"o":{"x":0.167,"y":0.167},"t":284,"s":[2.122,47.22,0],"to":[0,0,0],"ti":[0,0,0]},{"i":{"x":0.833,"y":0.833},"o":{"x":0.167,"y":0.167},"t":295,"s":[2.122,47.22,0],"to":[7.667,0,0],"ti":[-7.667,0,0]},{"i":{"x":0.833,"y":0.833},"o":{"x":0.167,"y":0.167},"t":298,"s":[48.122,47.22,0],"to":[0,0,0],"ti":[0,0,0]},{"i":{"x":0.833,"y":1},"o":{"x":0.167,"y":0},"t":311,"s":[48.122,47.22,0],"to":[0,-7.667,0],"ti":[0,7.667,0]},{"i":{"x":0.833,"y":0.833},"o":{"x":0.167,"y":0.167},"t":314,"s":[48.122,1.22,0],"to":[0,0,0],"ti":[0,0,0]},{"i":{"x":0.833,"y":1},"o":{"x":0.167,"y":0},"t":326,"s":[48.122,1.22,0],"to":[-7.333,0,0],"ti":[7.333,0,0]},{"i":{"x":0.833,"y":0.833},"o":{"x":0.167,"y":0.167},"t":329,"s":[4.122,1.22,0],"to":[0,0,0],"ti":[0,0,0]},{"i":{"x":0.833,"y":1},"o":{"x":0.167,"y":0},"t":341,"s":[4.122,1.22,0],"to":[0,7.667,0],"ti":[0,-7.667,0]},{"i":{"x":0.833,"y":0.833},"o":{"x":0.167,"y":0.167},"t":344,"s":[4.122,47.22,0],"to":[0,0,0],"ti":[0,0,0]},{"i":{"x":0.833,"y":0.833},"o":{"x":0.167,"y":0.167},"t":356,"s":[4.122,47.22,0],"to":[7,0,0],"ti":[-7,0,0]},{"i":{"x":0.833,"y":0.833},"o":{"x":0.167,"y":0.167},"t":359,"s":[46.122,47.22,0],"to":[0,0,0],"ti":[0,0,0]},{"i":{"x":0.833,"y":1},"o":{"x":0.167,"y":0},"t":371,"s":[46.122,47.22,0],"to":[0,-7.667,0],"ti":[0,7.667,0]},{"i":{"x":0.833,"y":0.833},"o":{"x":0.167,"y":0.167},"t":374,"s":[46.122,1.22,0],"to":[0,0,0],"ti":[0,0,0]},{"i":{"x":0.833,"y":1},"o":{"x":0.167,"y":0},"t":386,"s":[46.122,1.22,0],"to":[-7,0,0],"ti":[7,0,0]},{"i":{"x":0.833,"y":0.833},"o":{"x":0.167,"y":0.167},"t":389,"s":[4.122,1.22,0],"to":[0,0,0],"ti":[0,0,0]},{"i":{"x":0.833,"y":1},"o":{"x":0.167,"y":0},"t":401,"s":[4.122,1.22,0],"to":[0,8,0],"ti":[0,-8,0]},{"i":{"x":0.833,"y":0.833},"o":{"x":0.167,"y":0.167},"t":404,"s":[4.122,49.22,0],"to":[0,0,0],"ti":[0,0,0]},{"i":{"x":0.833,"y":0.833},"o":{"x":0.167,"y":0.167},"t":416,"s":[4.122,49.22,0],"to":[7,0,0],"ti":[-7,0,0]},{"i":{"x":0.833,"y":0.833},"o":{"x":0.167,"y":0.167},"t":419,"s":[46.122,49.22,0],"to":[0,0,0],"ti":[0,0,0]},{"i":{"x":0.833,"y":1},"o":{"x":0.167,"y":0},"t":431,"s":[46.122,49.22,0],"to":[0,-8,0],"ti":[0,8,0]},{"i":{"x":0.833,"y":0.833},"o":{"x":0.167,"y":0.167},"t":434,"s":[46.122,1.22,0],"to":[0,0,0],"ti":[0,0,0]},{"i":{"x":0.833,"y":1},"o":{"x":0.167,"y":0},"t":446,"s":[46.122,1.22,0],"to":[-7.333,0,0],"ti":[7.333,0,0]},{"i":{"x":0.833,"y":0.833},"o":{"x":0.167,"y":0.167},"t":449,"s":[2.122,1.22,0],"to":[0,0,0],"ti":[0,0,0]},{"i":{"x":0.833,"y":1},"o":{"x":0.167,"y":0},"t":461,"s":[2.122,1.22,0],"to":[0,8,0],"ti":[0,-8,0]},{"i":{"x":0.833,"y":0.833},"o":{"x":0.167,"y":0.167},"t":464,"s":[2.122,49.22,0],"to":[0,0,0],"ti":[0,0,0]},{"t":476,"s":[2.122,49.22,0]}],"ix":1,"l":2},"s":{"a":0,"k":[100,100,100],"ix":6,"l":2}},"ao":0,"sw":50,"sh":50,"sc":"#95d8f9","ip":-4,"op":491,"st":-4,"bm":0}],"markers":[]}